parse_prettytable/__init__.py
parse_prettytable/parse_prettytable.py
parse_prettytable-3.0.0.dist-info/METADATA
parse_prettytable-3.0.0.dist-info/WHEEL
parse_prettytable-3.0.0.dist-info/top_level.txt
parse_prettytable-3.0.0.dist-info/RECORD
