Metadata-Version: 2.1
Name: parse-prettytable
Version: 3.0.0
Summary: A python package for parsing prettytable strings
Home-page: UNKNOWN
Author: Kevin Zhang, Nana Zhan
Author-email: hr.zhang@gatech.edu
License: UNKNOWN
Keywords: python,prettytable,parse
Platform: UNKNOWN
Classifier: Intended Audience :: Education
Classifier: Programming Language :: Python :: 2
Classifier: Programming Language :: Python :: 3
Classifier: Operating System :: MacOS :: MacOS X
Classifier: Operating System :: Microsoft :: Windows
